[
  {
    "id": "1",
    "name": "iPhone 16 Pro",
    "brand": "Apple",
    "price": 119900,
    "images": [
      "/assets/products/iphone-16-pro-1774105841845-09cxj.png"
    ],
    "specs": [
      "6.3\" Display",
      "A18 Pro",
      "48MP Camera"
    ],
    "description": "Latest flagship iPhone with advanced AI features",
    "inStock": true,
    "condition": "Like New",
    "category": "flagship",
    "color": "Natural Titanium",
    "year": "2024",
    "storage": "256GB",
    "ram": "8GB",
    "stockQuantity": 2
  },
  {
    "id": "2",
    "name": "Galaxy S24 Ultra",
    "brand": "Samsung",
    "price": 124900,
    "images": [
      "/assets/products/galaxy-s24-ultra-1774105862816-5gurz.jpg"
    ],
    "specs": [
      "6.8\" Display",
      "Snapdragon 8 Gen 3",
      "200MP Camera"
    ],
    "description": "Premium Android experience with cutting-edge technology",
    "inStock": true,
    "condition": "Excellent",
    "category": "flagship",
    "color": "Titanium Gray",
    "year": "2024",
    "storage": "512GB",
    "ram": "12GB",
    "stockQuantity": 4
  },
  {
    "id": "3",
    "name": "Pixel 9 Pro XL",
    "brand": "Google",
    "price": 109900,
    "images": [
      "/assets/products/pixel-9-pro-xl-1774105883294-345h6.jpg"
    ],
    "specs": [
      "6.8\" LTPO OLED",
      "Tensor G4",
      "50MP Triple Camera"
    ],
    "description": "Google flagship with advanced AI camera and clean Android experience",
    "inStock": true,
    "condition": "Like New",
    "category": "flagship",
    "color": "Obsidian",
    "year": "2025",
    "storage": "256GB",
    "ram": "16GB",
    "stockQuantity": 6
  },
  {
    "id": "4",
    "name": "Xiaomi 14 Ultra",
    "brand": "Xiaomi",
    "price": 99900,
    "images": [
      "/assets/products/xiaomi-14-ultra-1774105897501-0ur6z.jpg"
    ],
    "specs": [
      "6.73\" AMOLED",
      "Snapdragon 8 Gen 3",
      "Leica Quad Camera"
    ],
    "description": "Premium camera-centric smartphone tuned for pro photography",
    "inStock": true,
    "condition": "Excellent",
    "category": "flagship",
    "color": "Black",
    "year": "2024",
    "storage": "512GB",
    "ram": "16GB",
    "stockQuantity": 3
  },
  {
    "id": "5",
    "name": "OnePlus 12",
    "brand": "OnePlus",
    "price": 69900,
    "images": [
      "/assets/products/oneplus-12-1774105917540-yazhl.jpg"
    ],
    "specs": [
      "6.82\" QHD AMOLED",
      "Snapdragon 8 Gen 3",
      "100W Fast Charging"
    ],
    "description": "Smooth flagship performance with ultra-fast charging and Hasselblad tuning",
    "inStock": true,
    "condition": "Excellent",
    "category": "flagship",
    "color": "Flowy Emerald",
    "year": "2024",
    "storage": "256GB",
    "ram": "12GB",
    "stockQuantity": 7
  },
  {
    "id": "6",
    "name": "Sony Xperia 1 VI",
    "brand": "Sony",
    "price": 119000,
    "images": [
      "/assets/products/sony-xperia-1-vi-1774105931443-9pqlr.jpg"
    ],
    "specs": [
      "6.5\" OLED 120Hz",
      "Snapdragon 8 Gen 3",
      "Creator-grade video tools"
    ],
    "description": "Cinema-inspired flagship for creators who want manual camera control",
    "inStock": false,
    "condition": "Like New",
    "category": "flagship",
    "color": "Khaki Green",
    "year": "2024",
    "storage": "256GB",
    "ram": "12GB",
    "stockQuantity": 0
  },
  {
    "name": "z fold 4",
    "brand": "Samsung",
    "price": 79999,
    "images": [
      "/assets/products/z-fold-4-1774261675628-04j8v.jpg"
    ],
    "specs": [
      "50MP Camera",
      "400mah",
      "a4 chip"
    ],
    "description": "",
    "inStock": false,
    "condition": "Excellent",
    "category": "flagship",
    "color": "Black ",
    "year": "2022",
    "storage": "128",
    "ram": "8 GB",
    "stockQuantity": 0,
    "id": "w61fu4hr1"
  }
]